conanio/__init__.py
conanio/packager.py
cpt/__init__.py
cpt/auth.py
cpt/builds_generator.py
cpt/ci_manager.py
cpt/config.py
cpt/log.py
cpt/packager.py
cpt/printer.py
cpt/profiles.py
cpt/remotes.py
cpt/requirements.txt
cpt/requirements_deploy.txt
cpt/requirements_test.txt
cpt/run_in_docker.py
cpt/runner.py
cpt/tools.py
cpt/uploader.py
cpt/test/__init__.py
cpt/test/assets/__init__.py
cpt/test/assets/genconanfile.py
cpt/test/integration/__init__.py
cpt/test/integration/base.py
cpt/test/integration/basic_test.py
cpt/test/integration/docker_test.py
cpt/test/integration/profile_test.py
cpt/test/integration/remotes_test.py
cpt/test/integration/require_overrides.py
cpt/test/integration/update_deps_test.py
cpt/test/integration/update_python_reqs_test.py
cpt/test/integration/update_some_deps_test.py
cpt/test/integration/upload_test.py
cpt/test/test_client/__init__.py
cpt/test/test_client/config_install_test.py
cpt/test/test_client/invalid_config_checks_test.py
cpt/test/test_client/tools.py
cpt/test/test_client/upload_checks_test.py
cpt/test/test_client/visual_toolsets_test.py
cpt/test/unit/__init__.py
cpt/test/unit/auth_test.py
cpt/test/unit/ci_manager_test.py
cpt/test/unit/config_test.py
cpt/test/unit/generators_test.py
cpt/test/unit/packager_test.py
cpt/test/unit/remotes_test.py
cpt/test/unit/utils.py
cpt/test/utils/__init__.py
cpt/test/utils/mocks.py
cpt/test/utils/scm.py
cpt/test/utils/server_launcher.py
cpt/test/utils/test_files.py
cpt/test/utils/tools.py
conan_package_tools-0.38.1.dist-info/LICENSE.md
conan_package_tools-0.38.1.dist-info/METADATA
conan_package_tools-0.38.1.dist-info/WHEEL
conan_package_tools-0.38.1.dist-info/entry_points.txt
conan_package_tools-0.38.1.dist-info/top_level.txt
conan_package_tools-0.38.1.dist-info/RECORD
